repen/__init__.py
repen/adapters/__init__.py
repen/adapters/base.py
repen/adapters/figure.py
repen/adapters/image.py
repen/adapters/metric.py
repen/adapters/registry.py
repen/adapters/table.py
repen/adapters/text.py
repen/components/__init__.py
repen/components/base.py
repen/components/figure.py
repen/components/generic.py
repen/components/image.py
repen/components/layout.py
repen/components/metric.py
repen/components/table.py
repen/components/text.py
repen/renderers/__init__.py
repen/renderers/base.py
repen/renderers/debug.py
repen/renderers/html/__init__.py
repen/renderers/html/datatable.py
repen/renderers/html/processor.py
repen/renderers/html/processor_figure.py
repen/renderers/html/processor_image.py
repen/renderers/html/processor_layout.py
repen/renderers/html/processor_metric.py
repen/renderers/html/processor_table.py
repen/renderers/html/processor_text.py
repen/renderers/html/renderer.py
repen/renderers/html/theme.py
repen/renderers/html/theme_default.py
repen/renderers/html/theme_registry.py
repen/report.py
repen-0.1.0.dist-info/LICENSE
repen-0.1.0.dist-info/METADATA
repen-0.1.0.dist-info/WHEEL
repen-0.1.0.dist-info/RECORD
