Metadata-Version: 2.3
Name: repen
Version: 0.1.0
Summary: Automation engine for report generation
License: MIT
Author: Aliaksandr Sharstniou
Author-email: a.sharstniou.dev@gmail.com
Requires-Python: >=3.12
Classifier: Programming Language :: Python :: 3
Classifier: Operating System :: OS Independent
